{
  "lastUpdate": "2022-12-28 22:40:21",
  "delay": [
    {
      "shortName": "710",
      "headSign": "Grabówek SKM 02",
      "delayDesc": "2 min",
      "delay": 97,
      "blink": false,
      "routeId": 10710,
      "raw": null,
      "sort": 0
    },
    {
      "shortName": "710",
      "headSign": "Grabówek SKM 02",
      "delayDesc": "7 min",
      "delay": 397,
      "blink": false,
      "routeId": 10710,
      "raw": null,
      "sort": 0
    },
    {
      "shortName": "R",
      "headSign": "Rumia Dworzec PKP 03",
      "delayDesc": "22:54",
      "delay": 817,
      "blink": false,
      "routeId": "10605",
      "tripId": "10033",
      "raw": null,
      "dzisiaj": null,
      "jutro": null,
      "wyjatki": null,
      "sort": 0
    },
    {
      "shortName": "710",
      "headSign": "Grabówek SKM 02",
      "delayDesc": "16 min",
      "delay": 937,
      "blink": false,
      "routeId": 10710,
      "raw": null,
      "sort": 0
    },
    {
      "shortName": "710",
      "headSign": "Grabówek SKM 02",
      "delayDesc": "20 min",
      "delay": 1177,
      "blink": false,
      "routeId": 10710,
      "raw": null,
      "sort": 0
    },
    {
      "shortName": "N10",
      "headSign": "Oksywie Dolne 01",
      "delayDesc": "23:17",
      "delay": 2197,
      "blink": false,
      "routeId": "10410",
      "tripId": "9581",
      "raw": null,
      "dzisiaj": null,
      "jutro": null,
      "wyjatki": null,
      "sort": 0
    },
    {
      "shortName": "710",
      "headSign": "Grabówek SKM 02",
      "delayDesc": "23:31",
      "delay": 3037,
      "blink": false,
      "routeId": "10710",
      "tripId": "10951",
      "raw": null,
      "dzisiaj": null,
      "jutro": null,
      "wyjatki": null,
      "sort": 0
    },
    {
      "shortName": "N30",
      "headSign": "Rumia Dworzec PKP 03",
      "delayDesc": "23:37",
      "delay": 3397,
      "blink": false,
      "routeId": "10430",
      "tripId": "9615",
      "raw": null,
      "dzisiaj": null,
      "jutro": null,
      "wyjatki": null,
      "sort": 0
    },
    {
      "shortName": "710",
      "headSign": "Grabówek SKM 02",
      "delayDesc": "23:56",
      "delay": 4537,
      "blink": false,
      "routeId": "10710",
      "tripId": "10845",
      "raw": null,
      "dzisiaj": null,
      "jutro": null,
      "wyjatki": null,
      "sort": 0
    },
    {
      "shortName": "N10",
      "headSign": "Oksywie Dolne 01",
      "delayDesc": "00:17",
      "delay": 5798,
      "blink": false,
      "routeId": "10410",
      "tripId": "9579",
      "raw": null,
      "dzisiaj": null,
      "jutro": null,
      "wyjatki": null,
      "sort": 1
    },
    {
      "shortName": "N10",
      "headSign": "Oksywie Dolne 01",
      "delayDesc": "01:17",
      "delay": 9398,
      "blink": false,
      "routeId": "10410",
      "tripId": "9583",
      "raw": null,
      "dzisiaj": null,
      "jutro": null,
      "wyjatki": null,
      "sort": 1
    },
    {
      "shortName": "N10",
      "headSign": "Oksywie Dolne 01",
      "delayDesc": "02:17",
      "delay": 12998,
      "blink": false,
      "routeId": "10410",
      "tripId": "9580",
      "raw": null,
      "dzisiaj": null,
      "jutro": null,
      "wyjatki": null,
      "sort": 1
    }
  ],
  "stopId": "33180"
}